CHANGES.rst
LICENSE
MANIFEST.in
README.rst
setup.py
wagtail_calendar/__init__.py
wagtail_calendar/urls.py
wagtail_calendar/utils.py
wagtail_calendar/views.py
wagtail_calendar/wagtail_hooks.py
wagtail_calendar.egg-info/PKG-INFO
wagtail_calendar.egg-info/SOURCES.txt
wagtail_calendar.egg-info/dependency_links.txt
wagtail_calendar.egg-info/not-zip-safe
wagtail_calendar.egg-info/top_level.txt
wagtail_calendar/static/wagtail_calendar/css/planning.css
wagtail_calendar/static/wagtail_calendar/fullcalendar/fullcalendar.css
wagtail_calendar/static/wagtail_calendar/fullcalendar/fullcalendar.js
wagtail_calendar/static/wagtail_calendar/fullcalendar/fullcalendar.min.css
wagtail_calendar/static/wagtail_calendar/fullcalendar/fullcalendar.min.js
wagtail_calendar/static/wagtail_calendar/fullcalendar/locale-all.js
wagtail_calendar/static/wagtail_calendar/js/planning.js
wagtail_calendar/static/wagtail_calendar/moment/moment.min.js
wagtail_calendar/templates/wagtail_calendar/planning_calendar.html
wagtail_calendar/templatetags/__init__.py
wagtail_calendar/templatetags/wagtail_calendar_utils.py
wagtail_calendar/tests/__init__.py
wagtail_calendar/tests/settings.py
wagtail_calendar/tests/test_hooks.py
wagtail_calendar/tests/test_views.py
wagtail_calendar/tests/urls.py
wagtail_calendar/tests/utils.py