Metadata-Version: 1.0
Name: wagtail-calendar
Version: 1.0.3
Summary: A planning calendar for wagtail
Home-page: https://github.com/Gagaro/wagtail-calendar
Author: Gagaro
Author-email: gagaro42@gmail.com
License: BSD3
Platform: UNKNOWN
